imago/__init__.py
imago/__main__.py
imago/extractor.py
imago/hash.py
imago/helper.py
imago/imago.py
imago-1.0.5.dist-info/METADATA
imago-1.0.5.dist-info/RECORD
imago-1.0.5.dist-info/WHEEL
imago-1.0.5.dist-info/entry_points.txt
imago-1.0.5.dist-info/top_level.txt
