Metadata-Version: 2.1
Name: imago
Version: 1.0.5
Summary: Imago is a python tool that extract digital evidences from images.
Home-page: https://github.com/redaelli/imago-forensics
Author: Matteo Redaelli
Author-email: solventdev@gmail.com
License: UNKNOWN
Platform: UNKNOWN
Classifier: License :: OSI Approved :: MIT License
Classifier: Programming Language :: Python :: 2.7
Classifier: Programming Language :: Python :: Implementation :: PyPy
Requires-Python: >=2.7.0
Requires-Dist: exifread (==2.1.2)
Requires-Dist: python-magic (==0.4.15)
Requires-Dist: argparse (==1.4.0)
Requires-Dist: pillow (==5.2.0)
Requires-Dist: nudepy (==0.4)
Requires-Dist: imagehash (==4.0)
Requires-Dist: geopy (==1.16.0)
